{"id":"5539ac09-bfcd-4622-977a-569c13db9d7e","timestamp":1744902054658,"matcher":{"static":{"/api/content/projects_en/database.sql":{"prerender":true},"/api/content/projects_fr/database.sql":{"prerender":true},"/api/content/skills_en/database.sql":{"prerender":true},"/api/content/skills_fr/database.sql":{"prerender":true},"/api/content/docs_en/database.sql":{"prerender":true},"/api/content/docs_fr/database.sql":{"prerender":true}},"wildcard":{},"dynamic":{}},"prerendered":["/","/about","/projects","/skills/communication","/skills","/skills/symfony","/skills/architecture-sgbdr","/skills/git","/projects/mpa","/projects/apibook","/skills/architecture-logicielle","/contact","/projects/lands","/projects/spartacube","/projects/medicalplace","/skills/administration-systemes-linux","/skills/autonomie","/skills/empathie","/skills/travail_d_equipe","/skills/organisation"]}